codio/__init__.py
codio/__version__.py
codio/cli.py
codio-0.1.0.dist-info/LICENSE
codio-0.1.0.dist-info/METADATA
codio-0.1.0.dist-info/WHEEL
codio-0.1.0.dist-info/entry_points.txt
codio-0.1.0.dist-info/top_level.txt
codio-0.1.0.dist-info/RECORD
